gartersnake/__init__.py
gartersnake/conda.py
gartersnake/missing.py
gartersnake/pip.py
gartersnake/version.py
gartersnake/windows.py
gartersnake-1.0.1.dist-info/LICENSE
gartersnake-1.0.1.dist-info/METADATA
gartersnake-1.0.1.dist-info/WHEEL
gartersnake-1.0.1.dist-info/top_level.txt
gartersnake-1.0.1.dist-info/RECORD
