Metadata-Version: 2.1
Name: gartersnake
Version: 1.0.1
Summary: helpers for `setup.py`
Home-page: https://github.com/zacharyburnett/GarterSnake.git
License: MIT
Platform: UNKNOWN
Requires-Python: >=3.6
License-File: LICENSE
Provides-Extra: development
Requires-Dist: flake8 ; extra == 'development'
Requires-Dist: isort ; extra == 'development'
Requires-Dist: oitnb ; extra == 'development'
Provides-Extra: testing
Requires-Dist: pytest ; extra == 'testing'
Requires-Dist: pytest-cov ; extra == 'testing'
Requires-Dist: pytest-xdist ; extra == 'testing'
Requires-Dist: wget ; extra == 'testing'
